<annotation>
	<folder>Ai_car</folder>
	<filename>car1406.png</filename>
	<path>C:\Users\HyeonTaek-Lim\Desktop\Ai_car\car1406.png</path>
	<source>
		<database>Unknown</database>
	</source>
	<size>
		<width>0</width>
		<height>0</height>
		<depth>3</depth>
	</size>
	<segmented>0</segmented>
	<object>
		<name>car</name>
		<pose>Unspecified</pose>
		<truncated>0</truncated>
		<difficult>0</difficult>
		<bndbox>
			<xmin>705</xmin>
			<ymin>299</ymin>
			<xmax>3026</xmax>
			<ymax>2857</ymax>
		</bndbox>
	</object>
	<object>
		<name>plate</name>
		<pose>Unspecified</pose>
		<truncated>0</truncated>
		<difficult>0</difficult>
		<bndbox>
			<xmin>2468</xmin>
			<ymin>1008</ymin>
			<xmax>2738</xmax>
			<ymax>1990</ymax>
		</bndbox>
	</object>
</annotation>
